NiukeDichanXingyeQiuzhiGonglveLonghuPian20212022Fix1/README.md
NiukeDichanXingyeQiuzhiGonglveLonghuPian20212022Fix1/__init__.py
NiukeDichanXingyeQiuzhiGonglveLonghuPian20212022Fix1/__main__.py
NiukeDichanXingyeQiuzhiGonglveLonghuPian20212022Fix1/file.epub
NiukeDichanXingyeQiuzhiGonglveLonghuPian20212022Fix1/index.html
NiukeDichanXingyeQiuzhiGonglveLonghuPian20212022Fix1/css/__init__.py
NiukeDichanXingyeQiuzhiGonglveLonghuPian20212022Fix1/css/annotations.css
NiukeDichanXingyeQiuzhiGonglveLonghuPian20212022Fix1/css/main.css
NiukeDichanXingyeQiuzhiGonglveLonghuPian20212022Fix1/css/normalize.css
NiukeDichanXingyeQiuzhiGonglveLonghuPian20212022Fix1/css/popup.css
NiukeDichanXingyeQiuzhiGonglveLonghuPian20212022Fix1/font/__init__.py
NiukeDichanXingyeQiuzhiGonglveLonghuPian20212022Fix1/font/fontello.eot
NiukeDichanXingyeQiuzhiGonglveLonghuPian20212022Fix1/font/fontello.svg
NiukeDichanXingyeQiuzhiGonglveLonghuPian20212022Fix1/font/fontello.ttf
NiukeDichanXingyeQiuzhiGonglveLonghuPian20212022Fix1/font/fontello.woff
NiukeDichanXingyeQiuzhiGonglveLonghuPian20212022Fix1/img/__init__.py
NiukeDichanXingyeQiuzhiGonglveLonghuPian20212022Fix1/img/annotator-glyph-sprite.png
NiukeDichanXingyeQiuzhiGonglveLonghuPian20212022Fix1/img/annotator-icon-sprite.png
NiukeDichanXingyeQiuzhiGonglveLonghuPian20212022Fix1/img/apple-touch-icon.png
NiukeDichanXingyeQiuzhiGonglveLonghuPian20212022Fix1/img/cancelfullscreen.png
NiukeDichanXingyeQiuzhiGonglveLonghuPian20212022Fix1/img/close.png
NiukeDichanXingyeQiuzhiGonglveLonghuPian20212022Fix1/img/fullscreen.png
NiukeDichanXingyeQiuzhiGonglveLonghuPian20212022Fix1/img/loader.gif
NiukeDichanXingyeQiuzhiGonglveLonghuPian20212022Fix1/img/menu-icon.png
NiukeDichanXingyeQiuzhiGonglveLonghuPian20212022Fix1/img/save.png
NiukeDichanXingyeQiuzhiGonglveLonghuPian20212022Fix1/img/saved.png
NiukeDichanXingyeQiuzhiGonglveLonghuPian20212022Fix1/img/settings-s.png
NiukeDichanXingyeQiuzhiGonglveLonghuPian20212022Fix1/img/settings.png
niuke_dichan_xingye_qiuzhi_gonglve_longhu_pian_2021_2022_fix1-2025.3.25.1.dist-info/METADATA
niuke_dichan_xingye_qiuzhi_gonglve_longhu_pian_2021_2022_fix1-2025.3.25.1.dist-info/WHEEL
niuke_dichan_xingye_qiuzhi_gonglve_longhu_pian_2021_2022_fix1-2025.3.25.1.dist-info/entry_points.txt
niuke_dichan_xingye_qiuzhi_gonglve_longhu_pian_2021_2022_fix1-2025.3.25.1.dist-info/top_level.txt
niuke_dichan_xingye_qiuzhi_gonglve_longhu_pian_2021_2022_fix1-2025.3.25.1.dist-info/RECORD
